Workbook

Sheet Tableau de bord
A1: Tableau de bord financier — OASIS-V2
A2: Vue de contrôle alimentée par le registre Transactions; actualiser les formules dans Excel après saisie.
A4: Indicateurs financiers | D4: Suivi par catégorie
A5: Budget projet approuvé | B5: =SUM('Budget initial'!$D$5:$D$40) | D5: Catégorie | E5: Dépenses payées
A6: Aide OASIS approuvée | B6: ='Paramètres'!$B$5 | D6: Salaires et charges sociales | E6: =SUMIFS(Transactions!$N$5:$N$504,Transactions!$G$5:$G$504,D6,Transactions!$Q$5:$Q$504,"Payé")
A7: Dépenses engagées | B7: =SUMIF(Transactions!$Q$5:$Q$504,"Engagé",Transactions!$N$5:$N$504) | D7: Services externes | E7: =SUMIFS(Transactions!$N$5:$N$504,Transactions!$G$5:$G$504,D7,Transactions!$Q$5:$Q$504,"Payé")
A8: Dépenses payées | B8: =SUMIF(Transactions!$Q$5:$Q$504,"Payé",Transactions!$N$5:$N$504) | D8: Décontamination des sols | E8: =SUMIFS(Transactions!$N$5:$N$504,Transactions!$G$5:$G$504,D8,Transactions!$Q$5:$Q$504,"Payé")
A9: Financement OASIS saisi | B9: =SUM(Transactions!$O$5:$O$504) | D9: Activités de communication | E9: =SUMIFS(Transactions!$N$5:$N$504,Transactions!$G$5:$G$504,D9,Transactions!$Q$5:$Q$504,"Payé")
A10: Transactions à valider | B10: =COUNTIF(Transactions!$R$5:$R$504,"À valider") | D10: Frais de déplacement | E10: =SUMIFS(Transactions!$N$5:$N$504,Transactions!$G$5:$G$504,D10,Transactions!$Q$5:$Q$504,"Payé")
A11: Écart projet disponible | B11: =B5-B7-B8 | D11: Frais d'administration | E11: =SUMIFS(Transactions!$N$5:$N$504,Transactions!$G$5:$G$504,D11,Transactions!$Q$5:$Q$504,"Payé")
A12: Écart aide OASIS disponible | B12: =B6-B9 | D12: Frais techniques (matériaux) | E12: =SUMIFS(Transactions!$N$5:$N$504,Transactions!$G$5:$G$504,D12,Transactions!$Q$5:$Q$504,"Payé")
D13: Aménagement et équipement complémentaires fixes | E13: =SUMIFS(Transactions!$N$5:$N$504,Transactions!$G$5:$G$504,D13,Transactions!$Q$5:$Q$504,"Payé")
D14: Travaux de renforcement structuraux | E14: =SUMIFS(Transactions!$N$5:$N$504,Transactions!$G$5:$G$504,D14,Transactions!$Q$5:$Q$504,"Payé")
A16: Alerte | B16: =IF(B10>0,"Des transactions exigent une validation avant reddition.","Aucune transaction en attente de validation.")
A18: Notes de mise à jour
A19: Saisir ici les principales décisions financières, écarts, demandes d’autorisation ou conditions à vérifier à la prochaine rencontre du comité de suivi.

Sheet Guide
A1: Suivi financier — OASIS-V2
A2: Requalification verte du cœur de Val-d'Or et de ses milieux de vie
A4: Objet du classeur
A5: Ce classeur assure le suivi des dépenses, salaires, contrats, appels d'offres, revenus et pièces de preuve. Il est conçu pour soutenir les rapports financiers OASIS et ne remplace pas le budget approuvé par le Ministère.
A8: Procédure minimale
A9: 1 | B9: Saisir chaque facture, paie ou autre dépense dans l’onglet Transactions.
A10: 2 | B10: Lier la dépense à une catégorie, un code budgétaire, un projet et une pièce de preuve.
A11: 3 | B11: Mettre à jour les contrats et appels d’offres lorsque les engagements sont attribués.
A12: 4 | B12: Vérifier les alertes dans Tableau de bord et Contrôle admissibilité avant chaque rapport.
A13: 5 | B13: Conserver une copie des factures, autorisations, attestations, contrats et preuves de paiement pendant la durée exigée par la convention.
A16: Points de contrôle contractuels
A17: Élément | B17: Exigence de référence | C17: Contrôle dans le classeur
A18: Aide OASIS | B18: 6,755,514 $ maximum | C18: Tableau de bord / Budget initial
A19: Dépenses techniques | B19: Minimum de 50 % de l’aide financière totale | C19: Contrôle admissibilité
A20: Administration | B20: Maximum de 10 % de l’aide financière totale | C20: Contrôle admissibilité
A21: Communication | B21: Maximum de 2 % de l’aide financière totale | C21: Contrôle admissibilité
A22: Décontamination, renforcement, complémentaire | B22: Maximum de 5 % de l’aide financière totale chacun | C22: Contrôle admissibilité

Sheet Paramètres
A1: Paramètres de contrôle
A2: Valeurs de référence et listes déroulantes. Modifier seulement après validation de la direction de projet.
A3: Paramètre | B3: Valeur | C3: Source / note
E4: Catégories de dépenses | G4: Statuts | I4: Projets
A5: Montant maximal de l’aide OASIS | B5: 6755514 | C5: Convention, article 1 | E5: Salaires et charges sociales | G5: Brouillon | I5: P1 | J5: Terrain de baseball, 6e Avenue et atelier mécanique
A6: Coût total du projet | B6: 10385339 | C6: Budget approuvé, annexe B | E6: Services externes | G6: Engagé | I6: P2 | J6: Aréna Kiwanis et boulevard Lamaque
A7: Part OASIS prévue | B7: 0.65 | C7: Budget approuvé, annexe B | E7: Décontamination des sols | G7: Payé | I7: P3 | J7: Parc de l'Esker
A8: Part Ville / partenaires prévue | B8: 0.35 | C8: Budget approuvé, annexe B | E8: Activités de communication | G8: En attente de pièce | I8: Transversal | J8: Gestion, études, coordination et reddition de comptes
A9: Administration — plafond de l’aide | B9: 0.1 | C9: Convention, article 5 | E9: Frais de déplacement | G9: Non admissible
A10: Communication — plafond de l’aide | B10: 0.02 | C10: Convention, article 5 | E10: Frais d'administration | G10: À valider
A11: Décontamination — plafond de l’aide | B11: 0.05 | C11: Convention, article 5 | E11: Frais techniques (matériaux)
A12: Renforcement structural — plafond de l’aide | B12: 0.05 | C12: Convention, article 5 | E12: Aménagement et équipement complémentaires fixes
A13: Aménagement complémentaire — plafond de l’aide | B13: 0.05 | C13: Convention, article 5 | E13: Travaux de renforcement structuraux
A14: Frais techniques — minimum de l’aide | B14: 0.5 | C14: Convention, article 5 | E14: Non classée / à valider

Sheet Transactions
A1: Registre des transactions
A2: Saisir chaque dépense, engagement ou paie. Les colonnes orange nécessitent une validation avant la reddition.
A4: ID transaction | B4: Date facture | C4: Date engagement | D4: Date paiement | E4: # Facture / pièce | F4: Fournisseur / employé | G4: Catégorie | H4: Code budgétaire | I4: Projet | J4: Description | K4: Montant avant taxes | L4: TPS | M4: TVQ | N4: Total | O4: Financement OASIS | P4: Financement Ville / autres | Q4: Statut | R4: Admissibilité | S4: Preuve de paiement | T4: Lien / chemin de pièce | U4: Commentaires | V4: Validé par | W4: Date validation
A5: =IF(E5="","",ROW()-4) | N5: =IF(COUNTA(K5:M5)=0,"",SUM(K5:M5)) | P5: =IF(N5="","",N5-O5) | R5: =IF(E5="","",IF(Q5="Non admissible","Non",IF(AND(S5<>"",T5<>""),"Oui","À valider")))
A6: =IF(E6="","",ROW()-4) | N6: =IF(COUNTA(K6:M6)=0,"",SUM(K6:M6)) | P6: =IF(N6="","",N6-O6) | R6: =IF(E6="","",IF(Q6="Non admissible","Non",IF(AND(S6<>"",T6<>""),"Oui","À valider")))
A7: =IF(E7="","",ROW()-4) | N7: =IF(COUNTA(K7:M7)=0,"",SUM(K7:M7)) | P7: =IF(N7="","",N7-O7) | R7: =IF(E7="","",IF(Q7="Non admissible","Non",IF(AND(S7<>"",T7<>""),"Oui","À valider")))
A8: =IF(E8="","",ROW()-4) | N8: =IF(COUNTA(K8:M8)=0,"",SUM(K8:M8)) | P8: =IF(N8="","",N8-O8) | R8: =IF(E8="","",IF(Q8="Non admissible","Non",IF(AND(S8<>"",T8<>""),"Oui","À valider")))
A9: =IF(E9="","",ROW()-4) | N9: =IF(COUNTA(K9:M9)=0,"",SUM(K9:M9)) | P9: =IF(N9="","",N9-O9) | R9: =IF(E9="","",IF(Q9="Non admissible","Non",IF(AND(S9<>"",T9<>""),"Oui","À valider")))
A10: =IF(E10="","",ROW()-4) | N10: =IF(COUNTA(K10:M10)=0,"",SUM(K10:M10)) | P10: =IF(N10="","",N10-O10) | R10: =IF(E10="","",IF(Q10="Non admissible","Non",IF(AND(S10<>"",T10<>""),"Oui","À valider")))
A11: =IF(E11="","",ROW()-4) | N11: =IF(COUNTA(K11:M11)=0,"",SUM(K11:M11)) | P11: =IF(N11="","",N11-O11) | R11: =IF(E11="","",IF(Q11="Non admissible","Non",IF(AND(S11<>"",T11<>""),"Oui","À valider")))
A12: =IF(E12="","",ROW()-4) | N12: =IF(COUNTA(K12:M12)=0,"",SUM(K12:M12)) | P12: =IF(N12="","",N12-O12) | R12: =IF(E12="","",IF(Q12="Non admissible","Non",IF(AND(S12<>"",T12<>""),"Oui","À valider")))
A13: =IF(E13="","",ROW()-4) | N13: =IF(COUNTA(K13:M13)=0,"",SUM(K13:M13)) | P13: =IF(N13="","",N13-O13) | R13: =IF(E13="","",IF(Q13="Non admissible","Non",IF(AND(S13<>"",T13<>""),"Oui","À valider")))
A14: =IF(E14="","",ROW()-4) | N14: =IF(COUNTA(K14:M14)=0,"",SUM(K14:M14)) | P14: =IF(N14="","",N14-O14) | R14: =IF(E14="","",IF(Q14="Non admissible","Non",IF(AND(S14<>"",T14<>""),"Oui","À valider")))
A15: =IF(E15="","",ROW()-4) | N15: =IF(COUNTA(K15:M15)=0,"",SUM(K15:M15)) | P15: =IF(N15="","",N15-O15) | R15: =IF(E15="","",IF(Q15="Non admissible","Non",IF(AND(S15<>"",T15<>""),"Oui","À valider")))
A16: =IF(E16="","",ROW()-4) | N16: =IF(COUNTA(K16:M16)=0,"",SUM(K16:M16)) | P16: =IF(N16="","",N16-O16) | R16: =IF(E16="","",IF(Q16="Non admissible","Non",IF(AND(S16<>"",T16<>""),"Oui","À valider")))
... A504: =IF(E504="","",ROW()-4) | N504: =IF(COUNTA(K504:M504)=0,"",SUM(K504:M504)) | P504: =IF(N504="","",N504-O504) | R504: =IF(E504="","",IF(Q504="Non admissible","Non",IF(AND(S504<>"",T504<>""),"Oui","À valider")))

Sheet Budget initial
A1: Budget initial et suivi par poste
A2: Les montants initiaux sont extraits du budget OASIS fourni. Les sommes réelles sont alimentées par le registre Transactions.
A4: Catégorie | B4: Code | C4: Description | D4: Budget projet | E4: Budget OASIS | F4: Budget Ville / autres | G4: Engagé | H4: Payé | I4: Écart projet | J4: Écart OASIS | K4: Commentaire d’écart
A5: À classer | B5: 1.1 | C5: Direction générale (support 70 heures) (115$/h) | D5: 8050 | E5: 0 | F5: 8050 | G5: =SUMIFS(Transactions!$N$5:$N$504,Transactions!$H$5:$H$504,B5,Transactions!$Q$5:$Q$504,"Engagé") | H5: =SUMIFS(Transactions!$N$5:$N$504,Transactions!$H$5:$H$504,B5,Transactions!$Q$5:$Q$504,"Payé") | I5: =D5-G5-H5 | J5: =E5-SUMIFS(Transactions!$O$5:$O$504,Transactions!$H$5:$H$504,B5)
A6: À classer | B6: 1.2 | C6: Coordonateur en environnement (Chargé de projet OASIS) (840 heures) (70.54$/h) | D6: 59253 | E6: 59253 | F6: 0 | G6: =SUMIFS(Transactions!$N$5:$N$504,Transactions!$H$5:$H$504,B6,Transactions!$Q$5:$Q$504,"Engagé") | H6: =SUMIFS(Transactions!$N$5:$N$504,Transactions!$H$5:$H$504,B6,Transactions!$Q$5:$Q$504,"Payé") | I6: =D6-G6-H6 | J6: =E6-SUMIFS(Transactions!$O$5:$O$504,Transactions!$H$5:$H$504,B6)
A7: À classer | B7: 1.3 | C7: Tech génie civile (1500 heures) (54,13$/h) | D7: 81195 | E7: 81195 | F7: 0 | G7: =SUMIFS(Transactions!$N$5:$N$504,Transactions!$H$5:$H$504,B7,Transactions!$Q$5:$Q$504,"Engagé") | H7: =SUMIFS(Transactions!$N$5:$N$504,Transactions!$H$5:$H$504,B7,Transactions!$Q$5:$Q$504,"Payé") | I7: =D7-G7-H7 | J7: =E7-SUMIFS(Transactions!$O$5:$O$504,Transactions!$H$5:$H$504,B7)
A8: À classer | B8: 1.4 | C8: Coordonnateur gestion de projet ingénierie (420 heures) (70,54$/h) | D8: 29626 | E8: 29626 | F8: 0 | G8: =SUMIFS(Transactions!$N$5:$N$504,Transactions!$H$5:$H$504,B8,Transactions!$Q$5:$Q$504,"Engagé") | H8: =SUMIFS(Transactions!$N$5:$N$504,Transactions!$H$5:$H$504,B8,Transactions!$Q$5:$Q$504,"Payé") | I8: =D8-G8-H8 | J8: =E8-SUMIFS(Transactions!$O$5:$O$504,Transactions!$H$5:$H$504,B8)
A9: À classer | B9: 1.5 | C9: Géomaticien en support (80 heures) (65.64$/h) | D9: 5251 | E9: 0 | F9: 5251 | G9: =SUMIFS(Transactions!$N$5:$N$504,Transactions!$H$5:$H$504,B9,Transactions!$Q$5:$Q$504,"Engagé") | H9: =SUMIFS(Transactions!$N$5:$N$504,Transactions!$H$5:$H$504,B9,Transactions!$Q$5:$Q$504,"Payé") | I9: =D9-G9-H9 | J9: =E9-SUMIFS(Transactions!$O$5:$O$504,Transactions!$H$5:$H$504,B9)
A10: À classer | B10: 1.6 | C10: Travaux publics (directeur) (70 heures) (103.61$/h) | D10: 7252 | E10: 0 | F10: 7252 | G10: =SUMIFS(Transactions!$N$5:$N$504,Transactions!$H$5:$H$504,B10,Transactions!$Q$5:$Q$504,"Engagé") | H10: =SUMIFS(Transactions!$N$5:$N$504,Transactions!$H$5:$H$504,B10,Transactions!$Q$5:$Q$504,"Payé") | I10: =D10-G10-H10 | J10: =E10-SUMIFS(Transactions!$O$5:$O$504,Transactions!$H$5:$H$504,B10)
A11: À classer | B11: 1.7 | C11: Ingénieurs municipales (420 heures) (74.25$/h) | D11: 31290 | E11: 31290 | F11: 0 | G11: =SUMIFS(Transactions!$N$5:$N$504,Transactions!$H$5:$H$504,B11,Transactions!$Q$5:$Q$504,"Engagé") | H11: =SUMIFS(Transactions!$N$5:$N$504,Transactions!$H$5:$H$504,B11,Transactions!$Q$5:$Q$504,"Payé") | I11: =D11-G11-H11 | J11: =E11-SUMIFS(Transactions!$O$5:$O$504,Transactions!$H$5:$H$504,B11)
A12: À classer | B12: 1.8 | C12: Conseillière en urbanisme (840 heures) (59.67$/h) | D12: 50123 | E12: 0 | F12: 50123 | G12: =SUMIFS(Transactions!$N$5:$N$504,Transactions!$H$5:$H$504,B12,Transactions!$Q$5:$Q$504,"Engagé") | H12: =SUMIFS(Transactions!$N$5:$N$504,Transactions!$H$5:$H$504,B12,Transactions!$Q$5:$Q$504,"Payé") | I12: =D12-G12-H12 | J12: =E12-SUMIFS(Transactions!$O$5:$O$504,Transactions!$H$5:$H$504,B12)
A13: À classer | B13: 1.9 | C13: Trésorière (105 heures) (103.61$/h) | D13: 10879 | E13: 0 | F13: 10879 | G13: =SUMIFS(Transactions!$N$5:$N$504,Transactions!$H$5:$H$504,B13,Transactions!$Q$5:$Q$504,"Engagé") | H13: =SUMIFS(Transactions!$N$5:$N$504,Transactions!$H$5:$H$504,B13,Transactions!$Q$5:$Q$504,"Payé") | I13: =D13-G13-H13 | J13: =E13-SUMIFS(Transactions!$O$5:$O$504,Transactions!$H$5:$H$504,B13)
A14: À classer | B14: 1.10 | C14: Technicienne en administration (280 heures) (52,10$/h) | D14: 14588 | E14: 0 | F14: 14588 | G14: =SUMIFS(Transactions!$N$5:$N$504,Transactions!$H$5:$H$504,B14,Transactions!$Q$5:$Q$504,"Engagé") | H14: =SUMIFS(Transactions!$N$5:$N$504,Transactions!$H$5:$H$504,B14,Transactions!$Q$5:$Q$504,"Payé") | I14: =D14-G14-H14 | J14: =E14-SUMIFS(Transactions!$O$5:$O$504,Transactions!$H$5:$H$504,B14)
A15: À classer | B15: 1.11 | C15: Agent en communication (170 heures) (52.10$/h) | D15: 8857 | E15: 0 | F15: 8857 | G15: =SUMIFS(Transactions!$N$5:$N$504,Transactions!$H$5:$H$504,B15,Transactions!$Q$5:$Q$504,"Engagé") | H15: =SUMIFS(Transactions!$N$5:$N$504,Transactions!$H$5:$H$504,B15,Transactions!$Q$5:$Q$504,"Payé") | I15: =D15-G15-H15 | J15: =E15-SUMIFS(Transactions!$O$5:$O$504,Transactions!$H$5:$H$504,B15)
A16: À classer | B16: 2.1 | C16: Arpentage, relevés topographiques et implantation préliminaire | D16: 71000 | E16: 71000 | F16: 0 | G16: =SUMIFS(Transactions!$N$5:$N$504,Transactions!$H$5:$H$504,B16,Transactions!$Q$5:$Q$504,"Engagé") | H16: =SUMIFS(Transactions!$N$5:$N$504,Transactions!$H$5:$H$504,B16,Transactions!$Q$5:$Q$504,"Payé") | I16: =D16-G16-H16 | J16: =E16-SUMIFS(Transactions!$O$5:$O$504,Transactions!$H$5:$H$504,B16)
... A40: À classer | B40: 9.5 | C40: Licences bureautiques, outils collaboratifs, archivage, stockage et autres frais administratifs de support | D40: 34000 | E40: 34000 | F40: 0 | G40: =SUMIFS(Transactions!$N$5:$N$504,Transactions!$H$5:$H$504,B40,Transactions!$Q$5:$Q$504,"Engagé") | H40: =SUMIFS(Transactions!$N$5:$N$504,Transactions!$H$5:$H$504,B40,Transactions!$Q$5:$Q$504,"Payé") | I40: =D40-G40-H40 | J40: =E40-SUMIFS(Transactions!$O$5:$O$504,Transactions!$H$5:$H$504,B40)
A41: TOTAL | D41: =SUM(D5:D40) | E41: =SUM(E5:E40) | F41: =SUM(F5:F40) | G41: =SUM(G5:G40) | H41: =SUM(H5:H40) | I41: =SUM(I5:I40) | J41: =SUM(J5:J40)

Sheet Contrats
A1: Contrats et mandats professionnels
A2: Enregistrer les mandats, avenants, fournisseurs et montants engagés. Relier chaque entrée aux codes du budget.
A4: ID contrat | B4: Projet | C4: Fournisseur | D4: Objet / mandat | E4: Mode d’octroi | F4: Référence AO | G4: Date attribution | H4: Début | I4: Fin prévue | J4: Montant initial | K4: Avenants | L4: Montant révisé | M4: Code budget principal | N4: Statut | O4: Responsable municipal | P4: Lien / chemin du contrat | Q4: Commentaires
A5: =IF(C5="","","CTR-"&TEXT(ROW()-4,"000")) | L5: =IF(COUNTA(J5:K5)=0,"",J5+K5)
A6: =IF(C6="","","CTR-"&TEXT(ROW()-4,"000")) | L6: =IF(COUNTA(J6:K6)=0,"",J6+K6)
A7: =IF(C7="","","CTR-"&TEXT(ROW()-4,"000")) | L7: =IF(COUNTA(J7:K7)=0,"",J7+K7)
A8: =IF(C8="","","CTR-"&TEXT(ROW()-4,"000")) | L8: =IF(COUNTA(J8:K8)=0,"",J8+K8)
A9: =IF(C9="","","CTR-"&TEXT(ROW()-4,"000")) | L9: =IF(COUNTA(J9:K9)=0,"",J9+K9)
A10: =IF(C10="","","CTR-"&TEXT(ROW()-4,"000")) | L10: =IF(COUNTA(J10:K10)=0,"",J10+K10)
A11: =IF(C11="","","CTR-"&TEXT(ROW()-4,"000")) | L11: =IF(COUNTA(J11:K11)=0,"",J11+K11)
A12: =IF(C12="","","CTR-"&TEXT(ROW()-4,"000")) | L12: =IF(COUNTA(J12:K12)=0,"",J12+K12)
A13: =IF(C13="","","CTR-"&TEXT(ROW()-4,"000")) | L13: =IF(COUNTA(J13:K13)=0,"",J13+K13)
A14: =IF(C14="","","CTR-"&TEXT(ROW()-4,"000")) | L14: =IF(COUNTA(J14:K14)=0,"",J14+K14)
A15: =IF(C15="","","CTR-"&TEXT(ROW()-4,"000")) | L15: =IF(COUNTA(J15:K15)=0,"",J15+K15)
A16: =IF(C16="","","CTR-"&TEXT(ROW()-4,"000")) | L16: =IF(COUNTA(J16:K16)=0,"",J16+K16)
... A154: =IF(C154="","","CTR-"&TEXT(ROW()-4,"000")) | L154: =IF(COUNTA(J154:K154)=0,"",J154+K154)

Sheet Appels d’offres
A1: Appels d’offres et acquisitions
A2: Suivre la planification, publication, analyse, attribution et archivage des appels d’offres reliés au projet.
A4: ID AO | B4: Projet | C4: Objet | D4: Type | E4: Budget estimé | F4: Code budget | G4: Responsable | H4: Publication prévue | I4: Publication réelle | J4: Clôture | K4: Analyse | L4: Attribution | M4: Statut | N4: Contrat lié | O4: Pièces / lien | P4: Commentaires
A5: =IF(C5="","","AO-"&TEXT(ROW()-4,"000"))
A6: =IF(C6="","","AO-"&TEXT(ROW()-4,"000"))
A7: =IF(C7="","","AO-"&TEXT(ROW()-4,"000"))
A8: =IF(C8="","","AO-"&TEXT(ROW()-4,"000"))
A9: =IF(C9="","","AO-"&TEXT(ROW()-4,"000"))
A10: =IF(C10="","","AO-"&TEXT(ROW()-4,"000"))
A11: =IF(C11="","","AO-"&TEXT(ROW()-4,"000"))
A12: =IF(C12="","","AO-"&TEXT(ROW()-4,"000"))
A13: =IF(C13="","","AO-"&TEXT(ROW()-4,"000"))
A14: =IF(C14="","","AO-"&TEXT(ROW()-4,"000"))
A15: =IF(C15="","","AO-"&TEXT(ROW()-4,"000"))
A16: =IF(C16="","","AO-"&TEXT(ROW()-4,"000"))
... A154: =IF(C154="","","AO-"&TEXT(ROW()-4,"000"))

Sheet Salaires
A1: Feuilles de temps et salaires admissibles
A2: Saisir les heures et charges directement imputables au projet, avec preuve de paie et code budgétaire.
A4: ID paie | B4: Période début | C4: Période fin | D4: Employé / fonction | E4: Projet | F4: Code budget | G4: Heures | H4: Taux horaire | I4: Salaire brut | J4: Charges sociales | K4: Coût total | L4: Preuve de paie | M4: Statut | N4: Commentaires
A5: =IF(D5="","","PAIE-"&TEXT(ROW()-4,"000")) | I5: =IF(OR(G5="",H5=""),"",G5*H5) | K5: =IF(I5="","",I5+J5)
A6: =IF(D6="","","PAIE-"&TEXT(ROW()-4,"000")) | I6: =IF(OR(G6="",H6=""),"",G6*H6) | K6: =IF(I6="","",I6+J6)
A7: =IF(D7="","","PAIE-"&TEXT(ROW()-4,"000")) | I7: =IF(OR(G7="",H7=""),"",G7*H7) | K7: =IF(I7="","",I7+J7)
A8: =IF(D8="","","PAIE-"&TEXT(ROW()-4,"000")) | I8: =IF(OR(G8="",H8=""),"",G8*H8) | K8: =IF(I8="","",I8+J8)
A9: =IF(D9="","","PAIE-"&TEXT(ROW()-4,"000")) | I9: =IF(OR(G9="",H9=""),"",G9*H9) | K9: =IF(I9="","",I9+J9)
A10: =IF(D10="","","PAIE-"&TEXT(ROW()-4,"000")) | I10: =IF(OR(G10="",H10=""),"",G10*H10) | K10: =IF(I10="","",I10+J10)
A11: =IF(D11="","","PAIE-"&TEXT(ROW()-4,"000")) | I11: =IF(OR(G11="",H11=""),"",G11*H11) | K11: =IF(I11="","",I11+J11)
A12: =IF(D12="","","PAIE-"&TEXT(ROW()-4,"000")) | I12: =IF(OR(G12="",H12=""),"",G12*H12) | K12: =IF(I12="","",I12+J12)
A13: =IF(D13="","","PAIE-"&TEXT(ROW()-4,"000")) | I13: =IF(OR(G13="",H13=""),"",G13*H13) | K13: =IF(I13="","",I13+J13)
A14: =IF(D14="","","PAIE-"&TEXT(ROW()-4,"000")) | I14: =IF(OR(G14="",H14=""),"",G14*H14) | K14: =IF(I14="","",I14+J14)
A15: =IF(D15="","","PAIE-"&TEXT(ROW()-4,"000")) | I15: =IF(OR(G15="",H15=""),"",G15*H15) | K15: =IF(I15="","",I15+J15)
A16: =IF(D16="","","PAIE-"&TEXT(ROW()-4,"000")) | I16: =IF(OR(G16="",H16=""),"",G16*H16) | K16: =IF(I16="","",I16+J16)
... A304: =IF(D304="","","PAIE-"&TEXT(ROW()-4,"000")) | I304: =IF(OR(G304="",H304=""),"",G304*H304) | K304: =IF(I304="","",I304+J304)

Sheet Contrôle admissibilité
A1: Contrôle d’admissibilité et plafonds
A2: Les contrôles sont des signaux de gestion. Toute conclusion officielle doit être confirmée par la direction de projet et, au besoin, par le Ministère.
A4: Catégorie / règle | B4: Dépenses réelles | C4: Seuil contractuel | D4: Écart / marge | E4: Statut | F4: Observation
A5: Aide OASIS totale | B5: =SUM(Transactions!$O$5:$O$504) | C5: ='Paramètres'!$B$5 | D5: =C5-B5 | E5: =IF(B5<=C5,"Conforme","Dépassement") | F5: Vérifier que le financement OASIS total ne dépasse pas l’aide maximale.
A6: Frais d'administration | B6: =SUMIFS(Transactions!$N$5:$N$504,Transactions!$G$5:$G$504,"Frais d’administration") | C6: ='Paramètres'!$B$5*'Paramètres'!$B$9 | D6: =C6-B6 | E6: =IF(B6<=C6,"Conforme","Dépassement") | F6: Plafond de 10 % de l’aide financière.
A7: Activités de communication | B7: =SUMIFS(Transactions!$N$5:$N$504,Transactions!$G$5:$G$504,"Activités de communication") | C7: ='Paramètres'!$B$5*'Paramètres'!$B$10 | D7: =C7-B7 | E7: =IF(B7<=C7,"Conforme","Dépassement") | F7: Plafond de 2 % de l’aide financière.
A8: Décontamination des sols | B8: =SUMIFS(Transactions!$N$5:$N$504,Transactions!$G$5:$G$504,"Décontamination des sols") | C8: ='Paramètres'!$B$5*'Paramètres'!$B$11 | D8: =C8-B8 | E8: =IF(B8<=C8,"Conforme","Dépassement") | F8: Plafond de 5 % de l’aide financière.
A9: Renforcement structural | B9: =SUMIFS(Transactions!$N$5:$N$504,Transactions!$G$5:$G$504,"Travaux de renforcement structuraux") | C9: ='Paramètres'!$B$5*'Paramètres'!$B$12 | D9: =C9-B9 | E9: =IF(B9<=C9,"Conforme","Dépassement") | F9: Plafond de 5 % de l’aide financière.
A10: Aménagement complémentaire fixe | B10: =SUMIFS(Transactions!$N$5:$N$504,Transactions!$G$5:$G$504,"Aménagement et équipement complémentaires fixes") | C10: ='Paramètres'!$B$5*'Paramètres'!$B$13 | D10: =C10-B10 | E10: =IF(B10<=C10,"Conforme","Dépassement") | F10: Plafond de 5 % de l’aide financière.
A11: Frais techniques (matériaux) | B11: =SUMIFS(Transactions!$N$5:$N$504,Transactions!$G$5:$G$504,"Frais techniques (matériaux)") | C11: ='Paramètres'!$B$5*'Paramètres'!$B$14 | D11: =B11-C11 | E11: =IF(B11>=C11,"Conforme","Sous le minimum") | F11: Minimum de 50 % de l’aide financière; vérifier le classement des dépenses.
A12: Transactions à valider | B12: =COUNTIF(Transactions!$R$5:$R$504,"À valider") | C12: 0 | D12: =C12-B12 | E12: =IF(B12=0,"Conforme","Validation requise") | F12: Chaque transaction doit être accompagnée de pièces suffisantes.

Sheet Projets
A1: Projets sélectionnés — référence
A2: Données de référence extraites du rapport final du 21 mai 2026. Les résultats finaux devront être confirmés par les plans et le SIG.
A4: Code | B4: Projet | C4: Superficie IV cible (ha) | D4: Rétention quantitative (m³) | E4: Lame d’eau gérée (mm) | F4: Bassin versant (ha) | G4: Imperméabilisation | H4: Taux IV / BV | I4: Arbres proposés | J4: Budget classe D | K4: Dépenses admissibles estimées | L4: Source
A5: P1 | B5: Terrain de baseball, 6e Avenue et atelier mécanique | C5: 0.29 | D5: 1127 | E5: 91 | F5: 2.58 | G5: 0.48 | H5: 0.11 | I5: 204 | J5: 3851800 | K5: 1983900 | L5: Rapport final 2026-05-21, pages 27-29
A6: P2 | B6: Aréna Kiwanis et boulevard Lamaque | C6: 0.22 | D6: 480 | F6: 2 | I6: 105 | J6: 1810100 | K6: 1218250 | L6: Rapport final 2026-05-21, pages 32-34
A7: P3 | B7: Parc de l'Esker | C7: 0.9 | D7: 1992 | E7: 107 | F7: 4.98 | G7: 0.37 | H7: 0.18 | I7: 89 | J7: 1816000 | K7: 1716700 | L7: Rapport final 2026-05-21, pages 37-39

Sheet Obligations
A1: Obligations de reddition de comptes
A2: Registre de référence à mettre à jour par le coordonnateur. Les dates absolues dépendent de la date officielle de début des activités et de la signature.
A4: ID | B4: Exigence | C4: Échéance contractuelle | D4: Déclencheur / calcul | E4: Livrables / preuve | F4: Responsable | G4: Statut | H4: Commentaire
A5: O-01 | B5: Rapport annuel sur l’avancement des dépenses | C5: 31 mars de chaque exercice | D5: Chaque année financière, pendant la durée du projet | E5: Budget Excel, état des dépenses et revenus, pièces justificatives | F5: Analyste financier / Rédacteur | G5: À planifier
A6: O-02 | B6: Plan de suivi et d’évaluation (PSE) | C6: 75 jours après la signature | D6: Signature de la convention par les parties | E6: PSE, tableau des résultats, méthode, partenariats, bibliographie | F6: PSE et SIG / Rédacteur | G6: À préparer
A7: O-03 | B7: Rapport d’étape 1 | C7: 12 mois après le début des activités | D7: Date réelle de début selon calendrier officiel | E7: État activités, PSE à jour, états financiers, calendrier, évaluation de résilience | F7: Rédacteur / Finances / PSE | G7: À planifier
A8: O-04 | B8: Rapport d’étape 2 | C8: 24 mois après le début des activités | D8: Date réelle de début selon calendrier officiel | E8: État activités, PSE à jour, états financiers, calendrier ajusté si requis | F8: Rédacteur / Finances / PSE | G8: À planifier
A9: O-05 | B9: Rapport final | C9: 60 jours après la fin des activités | D9: Date réelle de fin du projet | E9: Plan entretien, résultats, bilan, rapport budgétaire, audit, leçons apprises | F9: Rédacteur / Finances / Comité | G9: À planifier
A10: O-06 | B10: Conservation des dossiers | C10: 6 ans après l’expiration | D10: Fin de la convention | E10: Documents et données liés à l’aide financière | F10: Coordonnateur / Archives | G10: À planifier
